controller.v
module controller (
    LdA, LdB, LdXout, enable_comp, incP, sel_mux_X, clearP, eqz, start, done, clock, ALU_sub
);
    input clock, eqz, start;
    output reg LdA, LdB, LdP, LdXout, enable_comp, sel_mux_X, incP, clearP, done, ALU_sub;

    parameter S0 = 3'b000, S1 = 3'b001, S2 = 3'b010, S3 = 3'b011, S4 = 3'b100, S5 = 3'b101, S6 = 3'b110, S7 = 3'b111;
    
    reg [2:0] state;

    always @(posedge clock) begin
        if (state === 3'bxxx)
          state <= S0;
        case (state)
            S0: if(start == 1) state <= S1;
            S1: state <= S2;
            S2: state <= S3;
            S3: state <= S4;
            S4: state <= S5;
            S5: state <= S6;
            S6:begin
                if(eqz == 1) state<= S7;
                else state<= S4;
            end
            S7: state <= S7;
            default: state <= S0;
        endcase
    end



    always @(state) begin
        case (state)
            S0: begin
                 LdA = 0; LdB = 0; LdXout = 0; enable_comp = 0; clearP = 0; incP = 0; done = 0; sel_mux_X = 0; ALU_sub = 0;
            end 

            S1:  LdA = 1; 

            S2: begin  LdA = 0;  #1 LdB = 1; clearP = 1; end

            S3: begin  enable_comp = 1; LdB = 0; sel_mux_X = 1; LdXout = 1; clearP = 0;end

            S4: begin  enable_comp = 0; ALU_sub = 0; sel_mux_X = 0; LdXout = 0; end

            S5: begin  incP = 1; ALU_sub = 1; LdXout = 1; end

            S6: begin  incP = 0; LdXout = 0; end

            S7: done = 1; 
        endcase
    end
endmodule

comp_eqz.v
module comp_eqz (
    eqz, in
);
    input [15:0] in;
    output eqz;
    
    assign eqz = in? 0 : 1;
endmodule

countP.v
module countP(Pout, incP, clearP, clock);
    input  clock, clearP, incP;
    output reg [15:0] Pout;

    always @(posedge clock) begin
        if(clearP == 1) Pout <= 0;
        else if(incP == 1) Pout <= Pout + 1; 
    end

endmodule

subtractor.v
module subtractor(out, inputA, inputB, ALU_sub); 
    input [15:0] inputA, inputB;
    input  clock, ALU_sub;
    output reg [15:0] out;

    always @(ALU_sub) 
        if(ALU_sub == 1) begin out = inputA - inputB; end
    always @(ALU_sub) begin
       // $display(" %d - %d = %d", inputA, inputB, out);
    end
endmodule

mux.v
module mux(out, in1, in0, select); 
    input [15:0] in1, in0;
    input select;
    output  [15:0] out;


    assign out = select? in1 : in0;
    always @(in0 or in1 or select) begin
    #0;  // zero‐delay lets the assign settle
        //$display("Currently selecting between %0d and %0d with select %b and selected %0d",in0, in1, select, out);
    end

endmodule

comp_gt.v
// This is a compartator which compares whether A > B or not
// If A > B then out = 1 else 0;
// this will require two variables gt and eq
// gt will determine whether A[i] > B[i] or not if true then 1 => a[i] $ ~b[i] {Everything is in binary} 
// Also for bits below MSB we also need to & eq[i+1] so that we know that the above bits were equal
// eq will determine whether a[i] and b[i] are equal or not => ~(a[i] ^ b[i])
// we will do this for all bits until we get wq[i] not equal to zero then we will see gt[i] and tell whether A > B is true or not
// After this we will break the loop

module comp_gt(out, inputA, inputB, clock, enable); 
    input [15:0] inputA, inputB;
    input clock, enable;
    output reg out;

    reg [15:0] gt, eq;
    integer i;

    always @(*) begin
        if(enable == 1) begin
            //$display("Comparing A and B");
            for (i=15; i>-1; i=i-1) begin 
                gt[i] = inputA[i] & (~inputB[i]);
                eq[i] = ~(inputA[i] ^ inputB[i]);

                if(eq[i] == 0) begin
                    if(gt[i] == 1)
                        out  = 1;
                    else 
                        out  = 0;
                    i = -1;
                end
            end
            //$display("Compared %d and %d", inputA, inputB);
        end
        
    end


endmodule

pipoX.v
// This is a parallel in parallel out module 

module pipoX(out, in, load, clock);
    input [15:0] in;
    input load, clock;
    output reg [15:0] out;

    always @(posedge clock) begin 
        if(load == 1) begin
            out <= in;
          //  $display("Currently at PIPO_X %d and output %d", in, out);
             end
    end

endmodule

pipo.v
// This is a parallel in parallel out module 

module pipo(out, in, load, clock);
    input [15:0] in;
    input load, clock;
    output reg [15:0] out;

    always @(posedge clock) begin 
        if(load == 1) begin
            out <= in;
            //$display("Currently at PIPO %d and output %d", in, out); 
            end
    end
 
endmodule

div_datapath.v
// Date : 29-07-2025
// FSM for datapath for division

module div_datapath(LdA, LdB, LdP, LdXout, enable_comp, sel_mux_X, clearP, incP, eqz, clock, data_in, ALU_sub, Pout);

    input LdA, LdB, LdP, clearP, incP, clock, enable_comp, LdXout, sel_mux_X, ALU_sub;
    input [15:0] data_in;
    output eqz;
    output [15:0] Pout;

    wire [15:0] Aout, Bout, X, Y, Xout, Pout, mux_X, mux_Y, mux_X2;
    wire gt_A_B, eqz;

    pipo A(Aout, data_in, LdA, clock);
    pipo B(Bout, data_in, LdB, clock);
    pipoX X_out(X, mux_X2, LdXout, clock);
    comp_gt COMP(gt_A_B, Aout, Bout, clock, enable_comp);
    mux X_m(mux_X, Aout, Bout,gt_A_B);
    mux Y_m(mux_Y, Aout, Bout, ~gt_A_B);
    mux X2_m(mux_X2, mux_X, Xout, sel_mux_X);
    subtractor SUB(Xout, X, mux_Y, ALU_sub);
    countP CNT(Pout, incP, clearP, clock);
    comp_eqz EQZ(eqz, X);



endmodule

test_div_datapath.v
module test_div_datapath;

    reg [15:0] data_in;
    reg clock, start;
    wire [15:0] Pout;

    div_datapath DIV(LdA, LdB, LdP, LdXout, enable_comp, sel_mux, clearP, incP, eqz, clock, data_in, ALU_sub, Pout);
    controller CNT(LdA, LdB, LdXout, enable_comp, incP, sel_mux, clearP, eqz, start, done, clock, ALU_sub);

    initial begin
        clock = 1'b0;
        #3 start = 1'b1;
        #500 $finish;
    end

    always #5 clock = ~clock;

    initial begin
        #12 data_in = 28;
        #18 data_in = 4;
    end

    initial begin
        //$monitor($time ," Done = %b", CNT.done);
        $dumpfile("div.vcd");
        $dumpvars(0,test_div_datapath);
    end

    always @(done) begin
        if(done == 1)
            $display("Answer = %d", DIV.Pout);
    end

endmodule

div.vcd
$date
	Wed Jul 30 17:12:23 2025
$end
$version
	Icarus Verilog
$end
$timescale
	1s
$end
$scope module test_div_datapath $end
$var wire 1 ! LdP $end
$var wire 1 " sel_mux $end
$var wire 1 # incP $end
$var wire 1 $ eqz $end
$var wire 1 % enable_comp $end
$var wire 1 & done $end
$var wire 1 ' clearP $end
$var wire 16 ( Pout [15:0] $end
$var wire 1 ) LdXout $end
$var wire 1 * LdB $end
$var wire 1 + LdA $end
$var wire 1 , ALU_sub $end
$var reg 1 - clock $end
$var reg 16 . data_in [15:0] $end
$var reg 1 / start $end
$scope module CNT $end
$var wire 1 - clock $end
$var wire 1 / start $end
$var wire 1 $ eqz $end
$var parameter 3 0 S0 $end
$var parameter 3 1 S1 $end
$var parameter 3 2 S2 $end
$var parameter 3 3 S3 $end
$var parameter 3 4 S4 $end
$var parameter 3 5 S5 $end
$var parameter 3 6 S6 $end
$var parameter 3 7 S7 $end
$var reg 1 , ALU_sub $end
$var reg 1 + LdA $end
$var reg 1 * LdB $end
$var reg 1 8 LdP $end
$var reg 1 ) LdXout $end
$var reg 1 ' clearP $end
$var reg 1 & done $end
$var reg 1 % enable_comp $end
$var reg 1 # incP $end
$var reg 1 " sel_mux_X $end
$var reg 3 9 state [2:0] $end
$upscope $end
$scope module DIV $end
$var wire 1 , ALU_sub $end
$var wire 1 + LdA $end
$var wire 1 * LdB $end
$var wire 1 ! LdP $end
$var wire 1 ) LdXout $end
$var wire 1 ' clearP $end
$var wire 1 - clock $end
$var wire 16 : data_in [15:0] $end
$var wire 1 % enable_comp $end
$var wire 1 # incP $end
$var wire 1 " sel_mux_X $end
$var wire 16 ; mux_Y [15:0] $end
$var wire 16 < mux_X2 [15:0] $end
$var wire 16 = mux_X [15:0] $end
$var wire 1 > gt_A_B $end
$var wire 1 $ eqz $end
$var wire 16 ? Xout [15:0] $end
$var wire 16 @ X [15:0] $end
$var wire 16 A Pout [15:0] $end
$var wire 16 B Bout [15:0] $end
$var wire 16 C Aout [15:0] $end
$scope module A $end
$var wire 1 - clock $end
$var wire 16 D in [15:0] $end
$var wire 1 + load $end
$var reg 16 E out [15:0] $end
$upscope $end
$scope module B $end
$var wire 1 - clock $end
$var wire 16 F in [15:0] $end
$var wire 1 * load $end
$var reg 16 G out [15:0] $end
$upscope $end
$scope module CNT $end
$var wire 1 ' clearP $end
$var wire 1 - clock $end
$var wire 1 # incP $end
$var reg 16 H Pout [15:0] $end
$upscope $end
$scope module COMP $end
$var wire 1 - clock $end
$var wire 1 % enable $end
$var wire 16 I inputA [15:0] $end
$var wire 16 J inputB [15:0] $end
$var reg 16 K eq [15:0] $end
$var reg 16 L gt [15:0] $end
$var reg 1 > out $end
$var integer 32 M i [31:0] $end
$upscope $end
$scope module EQZ $end
$var wire 16 N in [15:0] $end
$var wire 1 $ eqz $end
$upscope $end
$scope module SUB $end
$var wire 1 , ALU_sub $end
$var wire 1 O clock $end
$var wire 16 P inputB [15:0] $end
$var wire 16 Q inputA [15:0] $end
$var reg 16 R out [15:0] $end
$upscope $end
$scope module X2_m $end
$var wire 16 S in0 [15:0] $end
$var wire 1 " select $end
$var wire 16 T out [15:0] $end
$var wire 16 U in1 [15:0] $end
$upscope $end
$scope module X_m $end
$var wire 16 V in0 [15:0] $end
$var wire 16 W in1 [15:0] $end
$var wire 1 > select $end
$var wire 16 X out [15:0] $end
$upscope $end
$scope module X_out $end
$var wire 1 - clock $end
$var wire 16 Y in [15:0] $end
$var wire 1 ) load $end
$var reg 16 Z out [15:0] $end
$upscope $end
$scope module Y_m $end
$var wire 16 [ in0 [15:0] $end
$var wire 16 \ in1 [15:0] $end
$var wire 1 ] select $end
$var wire 16 ^ out [15:0] $end
$upscope $end
$upscope $end
$upscope $end
$enddefinitions $end
$comment Show the parameter values. $end
$dumpall
b111 7
b110 6
b101 5
b100 4
b11 3
b10 2
b1 1
b0 0
$end
#0
$dumpvars
bx ^
x]
bx \
bx [
bx Z
bx Y
bx X
bx W
bx V
bx U
bx T
bx S
bx R
bx Q
bx P
zO
bx N
bx M
bx L
bx K
bx J
bx I
bx H
bx G
bx F
bx E
bx D
bx C
bx B
bx A
bx @
bx ?
x>
bx =
bx <
bx ;
bx :
bx 9
x8
x/
bx .
0-
x,
x+
x*
x)
bx (
x'
x&
x%
x$
x#
x"
z!
$end
#3
1/
#5
0,
0"
0&
0#
0'
0%
0)
0*
0+
b0 9
1-
#10
0-
#12
b11100 .
b11100 :
b11100 D
b11100 F
#15
1+
b1 9
1-
#20
0-
#25
0+
b11100 C
b11100 E
b11100 I
b11100 W
b11100 \
b10 9
1-
#26
1'
1*
#30
0-
b100 .
b100 :
b100 D
b100 F
#35
0]
b11100 <
b11100 T
b11100 Y
1>
b111111111110xxxx K
b1xxxx L
b11111111111111111111111111111110 M
0'
1)
1"
0*
1%
b11100 =
b11100 U
b11100 X
b100 ;
b100 P
b100 ^
b11 9
b0 (
b0 A
b0 H
b100 B
b100 G
b100 J
b100 V
b100 [
1-
#40
0-
#45
0$
bx <
bx T
bx Y
0)
0"
0%
b11100 @
b11100 N
b11100 Q
b11100 Z
b100 9
1-
#50
0-
#55
b11000 <
b11000 T
b11000 Y
b11000 ?
b11000 R
b11000 S
1)
1,
1#
b101 9
1-
#60
0-
#65
0)
0#
b11000 @
b11000 N
b11000 Q
b11000 Z
b1 (
b1 A
b1 H
b110 9
1-
#70
0-
#75
0,
b100 9
1-
#80
0-
#85
b10100 <
b10100 T
b10100 Y
b10100 ?
b10100 R
b10100 S
1)
1,
1#
b101 9
1-
#90
0-
#95
0)
0#
b110 9
b10 (
b10 A
b10 H
b10100 @
b10100 N
b10100 Q
b10100 Z
1-
#100
0-
#105
0,
b100 9
1-
#110
0-
#115
b10000 <
b10000 T
b10000 Y
b10000 ?
b10000 R
b10000 S
1)
1,
1#
b101 9
1-
#120
0-
#125
0)
0#
b10000 @
b10000 N
b10000 Q
b10000 Z
b11 (
b11 A
b11 H
b110 9
1-
#130
0-
#135
0,
b100 9
1-
#140
0-
#145
b1100 <
b1100 T
b1100 Y
b1100 ?
b1100 R
b1100 S
1)
1,
1#
b101 9
1-
#150
0-
#155
0)
0#
b110 9
b100 (
b100 A
b100 H
b1100 @
b1100 N
b1100 Q
b1100 Z
1-
#160
0-
#165
0,
b100 9
1-
#170
0-
#175
b1000 <
b1000 T
b1000 Y
b1000 ?
b1000 R
b1000 S
1)
1,
1#
b101 9
1-
#180
0-
#185
0)
0#
b1000 @
b1000 N
b1000 Q
b1000 Z
b101 (
b101 A
b101 H
b110 9
1-
#190
0-
#195
0,
b100 9
1-
#200
0-
#205
b100 <
b100 T
b100 Y
b100 ?
b100 R
b100 S
1)
1,
1#
b101 9
1-
#210
0-
#215
0)
0#
b110 9
b110 (
b110 A
b110 H
b100 @
b100 N
b100 Q
b100 Z
1-
#220
0-
#225
0,
b100 9
1-
#230
0-
#235
b0 <
b0 T
b0 Y
b0 ?
b0 R
b0 S
1)
1,
1#
b101 9
1-
#240
0-
#245
1$
0)
0#
b0 @
b0 N
b0 Q
b0 Z
b111 (
b111 A
b111 H
b110 9
1-
#250
0-
#255
1&
b111 9
1-
